ultima_scraper_detector/__init__.py
ultima_scraper_detector/gui.py
ultima_scraper_detector/py.typed
ultima_scraper_detector/server.py
ultima_scraper_detector/ultima_scraper_detector.py
ultima_scraper_detector-0.1.51.dist-info/METADATA
ultima_scraper_detector-0.1.51.dist-info/WHEEL
ultima_scraper_detector-0.1.51.dist-info/RECORD
