Metadata-Version: 2.1
Name: ultima-scraper-detector
Version: 0.1.51
Summary: 
Author: UltimaHoarder
Author-email: 1285176+UltimaHoarder@users.noreply.github.com
Requires-Python: >=3.10,<4
Classifier: Programming Language :: Python :: 3
Classifier: Programming Language :: Python :: 3.10
Classifier: Programming Language :: Python :: 3.11
Classifier: Programming Language :: Python :: 3.12
Requires-Dist: fastapi (>=0.100.0,<1.0.0)
Requires-Dist: nudenet (>=3.0.8,<4.0.0)
Requires-Dist: pillow (>=10.1.0,<11.0.0)
Requires-Dist: psutil (>=5.9.6,<6.0.0)
Requires-Dist: uvicorn[standard] (>=0.25.0,<0.26.0)
